{
    "Name": "Full Circle",
    "StartPoint": {
      "X": 1123.11047,
      "Y": 41.4959679,
      "Z": 79.75613
    },
    "Props": [
      {
        "Name": "prop_tri_start_banner",
        "Position": {
          "X": 945.08905,
          "Y": -18.1980114,
          "Z": 77.76434
        },
        "Rotation": {
          "X": 0.0,
          "Y": 0.0,
          "Z": 0.0
        }
      },
      {
        "Name": "prop_tri_finish_banner",
        "Position": {
          "X": 1127.21265,
          "Y": 38.8055038,
          "Z": 79.75613
        },
        "Rotation": {
          "X": 0.0,
          "Y": 0.0,
          "Z": 0.0
        }
      }
    ],
    "WayPointList": [
      {
        "X": 880.675842,
        "Y": 22.8154335,
        "Z": 77.67883
      },
      {
        "X": 1029.374,
        "Y": 221.557831,
        "Z": 80.61742
      },
      {
        "X": 1104.04492,
        "Y": 418.105347,
        "Z": 90.49343
      },
      {
        "X": 1041.70911,
        "Y": 477.2605,
        "Z": 93.79577
      },
      {
        "X": 1048.10571,
        "Y": 506.871338,
        "Z": 94.4719238
      },
      {
        "X": 1259.396,
        "Y": 762.9328,
        "Z": 102.526482
      },
      {
        "X": 1295.83,
        "Y": 1527.50842,
        "Z": 96.11803
      },
      {
        "X": 891.8318,
        "Y": 2224.40381,
        "Z": 47.56013
      },
      {
        "X": 351.769318,
        "Y": 2529.172,
        "Z": 43.6010628
      },
      {
        "X": 226.159149,
        "Y": 3279.906,
        "Z": 40.1308136
      },
      {
        "X": 1303.16089,
        "Y": 3528.09619,
        "Z": 34.3281441
      },
      {
        "X": 2220.30151,
        "Y": 3808.87769,
        "Z": 32.8620071
      },
      {
        "X": 2499.832,
        "Y": 4103.28857,
        "Z": 37.2743874
      },
      {
        "X": 2466.78442,
        "Y": 4185.686,
        "Z": 36.187027
      },
      {
        "X": 2402.62622,
        "Y": 4648.0835,
        "Z": 35.7690964
      },
      {
        "X": 2200.24463,
        "Y": 4746.67041,
        "Z": 39.7701
      },
      {
        "X": 2141.65381,
        "Y": 4755.86328,
        "Z": 40.1871948
      },
      {
        "X": 2000.53027,
        "Y": 4628.12549,
        "Z": 40.1602859
      },
      {
        "X": 1674.3894,
        "Y": 4836.442,
        "Z": 41.0322952
      },
      {
        "X": 1955.178,
        "Y": 5138.1123,
        "Z": 42.32725
      },
      {
        "X": 2006.45764,
        "Y": 5163.64746,
        "Z": 46.0221634
      },
      {
        "X": 2420.06836,
        "Y": 5136.748,
        "Z": 45.84868
      },
      {
        "X": 2584.67065,
        "Y": 5098.30859,
        "Z": 43.7268257
      },
      {
        "X": 2678.056,
        "Y": 5121.625,
        "Z": 43.8007278
      },
      {
        "X": 2805.86572,
        "Y": 4898.138,
        "Z": 36.3540344
      },
      {
        "X": 2832.59375,
        "Y": 4423.152,
        "Z": 47.8087921
      },
      {
        "X": 2575.067,
        "Y": 4245.52441,
        "Z": 40.73795
      },
      {
        "X": 2069.33862,
        "Y": 3728.11523,
        "Z": 32.0400467
      },
      {
        "X": 1709.53088,
        "Y": 3518.894,
        "Z": 35.4531441
      },
      {
        "X": 1750.69519,
        "Y": 3408.18774,
        "Z": 37.24903
      },
      {
        "X": 2017.94177,
        "Y": 3091.86768,
        "Z": 46.0474548
      },
      {
        "X": 1992.50354,
        "Y": 2987.10571,
        "Z": 44.6976624
      },
      {
        "X": 1503.48059,
        "Y": 2752.086,
        "Z": 36.91223
      },
      {
        "X": 1261.5437,
        "Y": 2684.62158,
        "Z": 36.592247
      },
      {
        "X": 815.6334,
        "Y": 2698.1626,
        "Z": 39.418026
      },
      {
        "X": 797.254944,
        "Y": 2702.29761,
        "Z": 39.2571754
      },
      {
        "X": 33.9847336,
        "Y": 2768.19775,
        "Z": 57.0512772
      },
      {
        "X": -397.364532,
        "Y": 2870.26685,
        "Z": 39.0093536
      },
      {
        "X": -526.046265,
        "Y": 2849.276,
        "Z": 33.1401
      },
      {
        "X": -885.1647,
        "Y": 2752.92432,
        "Z": 22.5458164
      },
      {
        "X": -1324.17627,
        "Y": 2468.14673,
        "Z": 24.0298386
      },
      {
        "X": -1352.63293,
        "Y": 2367.55859,
        "Z": 33.95755
      },
      {
        "X": -1360.47412,
        "Y": 2203.39355,
        "Z": 49.0893478
      },
      {
        "X": -1270.41479,
        "Y": 2165.27344,
        "Z": 58.2357368
      },
      {
        "X": -851.735,
        "Y": 1881.0199,
        "Z": 158.267487
      },
      {
        "X": -814.1219,
        "Y": 1833.40491,
        "Z": 165.014572
      },
      {
        "X": -853.86,
        "Y": 1781.77283,
        "Z": 172.882263
      },
      {
        "X": -799.295166,
        "Y": 1662.67029,
        "Z": 197.915314
      },
      {
        "X": -751.460938,
        "Y": 1730.20227,
        "Z": 200.338074
      },
      {
        "X": -466.253754,
        "Y": 1987.70117,
        "Z": 206.889771
      },
      {
        "X": -179.703033,
        "Y": 1874.04907,
        "Z": 197.086426
      },
      {
        "X": -51.5821152,
        "Y": 1844.426,
        "Z": 200.706833
      },
      {
        "X": 141.508865,
        "Y": 1622.52161,
        "Z": 228.13356
      },
      {
        "X": 241.254868,
        "Y": 1307.50891,
        "Z": 235.438263
      },
      {
        "X": 307.697968,
        "Y": 1016.8432,
        "Z": 209.4578
      },
      {
        "X": 259.680634,
        "Y": 982.3102,
        "Z": 209.5368
      },
      {
        "X": -241.3992,
        "Y": 1061.30078,
        "Z": 234.726776
      },
      {
        "X": -464.475616,
        "Y": 900.3293,
        "Z": 237.903824
      },
      {
        "X": -709.869263,
        "Y": 992.7086,
        "Z": 237.002045
      },
      {
        "X": -767.3187,
        "Y": 974.0376,
        "Z": 236.4371
      },
      {
        "X": -1147.4657,
        "Y": 1020.66656,
        "Z": 204.853958
      },
      {
        "X": -1629.76306,
        "Y": 991.5562,
        "Z": 152.09137
      },
      {
        "X": -1628.85681,
        "Y": 1045.59106,
        "Z": 152.134521
      },
      {
        "X": -1606.35242,
        "Y": 1333.14954,
        "Z": 132.4884
      },
      {
        "X": -1422.66284,
        "Y": 1915.84558,
        "Z": 72.7076645
      },
      {
        "X": -1503.05,
        "Y": 2085.088,
        "Z": 58.0298843
      },
      {
        "X": -1526.45789,
        "Y": 2135.62256,
        "Z": 54.88967
      },
      {
        "X": -1535.907,
        "Y": 2183.793,
        "Z": 54.2303543
      },
      {
        "X": -1549.84949,
        "Y": 2322.785,
        "Z": 48.21868
      },
      {
        "X": -1676.235,
        "Y": 2417.472,
        "Z": 28.5806446
      },
      {
        "X": -1704.99072,
        "Y": 2439.4812,
        "Z": 29.4830551
      },
      {
        "X": -1925.23462,
        "Y": 2372.84985,
        "Z": 32.98375
      },
      {
        "X": -2065.424,
        "Y": 2323.7207,
        "Z": 36.3960724
      },
      {
        "X": -2078.75977,
        "Y": 2319.64722,
        "Z": 36.1836624
      },
      {
        "X": -2167.48047,
        "Y": 2311.19775,
        "Z": 33.851738
      },
      {
        "X": -2471.25854,
        "Y": 2297.19653,
        "Z": 30.1645241
      },
      {
        "X": -2682.54663,
        "Y": 2291.88477,
        "Z": 19.5656471
      },
      {
        "X": -2686.286,
        "Y": 2402.03735,
        "Z": 15.6889553
      },
      {
        "X": -2512.9585,
        "Y": 3510.82861,
        "Z": 13.2700834
      },
      {
        "X": -2318.91284,
        "Y": 4122.30957,
        "Z": 35.70332
      },
      {
        "X": -1781.92065,
        "Y": 4730.044,
        "Z": 56.0444336
      },
      {
        "X": -1323.31555,
        "Y": 5140.045,
        "Z": 60.73979
      },
      {
        "X": -674.1461,
        "Y": 5548.784,
        "Z": 37.3344154
      },
      {
        "X": -283.178619,
        "Y": 6084.40527,
        "Z": 30.23496
      },
      {
        "X": 582.519,
        "Y": 6533.066,
        "Z": 27.0476856
      },
      {
        "X": 1647.44678,
        "Y": 6371.718,
        "Z": 28.9554825
      },
      {
        "X": 2414.939,
        "Y": 5687.92969,
        "Z": 44.2702332
      },
      {
        "X": 2696.94385,
        "Y": 4738.526,
        "Z": 43.43324
      },
      {
        "X": 2867.573,
        "Y": 4138.984,
        "Z": 49.3292732
      },
      {
        "X": 2325.857,
        "Y": 2861.04,
        "Z": 39.8493576
      },
      {
        "X": 1941.57,
        "Y": 2537.34,
        "Z": 53.59
      },
      {
        "X": 1809.88977,
        "Y": 2316.74414,
        "Z": 56.0427971
      },
      {
        "X": 1703.382,
        "Y": 1547.5575,
        "Z": 83.72609
      },
      {
        "X": 1300.51318,
        "Y": 606.455566,
        "Z": 79.1918945
      },
      {
        "X": 779.5142,
        "Y": 39.8253937,
        "Z": 64.60428
      },
      {
        "X": 639.26,
        "Y": -227.18,
        "Z": 42.38
      },
      {
        "X": 604.025269,
        "Y": -281.63385,
        "Z": 38.8415756
      },
      {
        "X": 533.967041,
        "Y": -361.9429,
        "Z": 34.32034
      },
      {
        "X": 481.013672,
        "Y": -414.888,
        "Z": 37.24096
      },
      {
        "X": 328.320068,
        "Y": -475.6199,
        "Z": 32.8705521
      },
      {
        "X": 40.18097,
        "Y": -487.093048,
        "Z": 32.9741364
      },
      {
        "X": -811.6903,
        "Y": -495.217621,
        "Z": 23.8625164
      },
      {
        "X": -1162.05432,
        "Y": -647.454468,
        "Z": 9.96896648
      },
      {
        "X": -1743.47876,
        "Y": -640.141052,
        "Z": 9.364643
      },
      {
        "X": -2114.41577,
        "Y": -355.017944,
        "Z": 12.0222445
      },
      {
        "X": -2136.469,
        "Y": -269.788147,
        "Z": 13.35691
      },
      {
        "X": -1659.43359,
        "Y": -348.3986,
        "Z": 48.5742264
      },
      {
        "X": -1434.92041,
        "Y": -81.26073,
        "Z": 51.1773071
      },
      {
        "X": -1416.76477,
        "Y": -34.74446,
        "Z": 51.79803
      },
      {
        "X": -1211.19238,
        "Y": 233.725708,
        "Z": 66.43021
      },
      {
        "X": -692.112244,
        "Y": 242.110641,
        "Z": 79.96924
      },
      {
        "X": -10.0059414,
        "Y": 258.944183,
        "Z": 107.678284
      },
      {
        "X": 476.148956,
        "Y": 94.97271,
        "Z": 96.655014
      },
      {
        "X": 544.942,
        "Y": 157.546539,
        "Z": 98.23378
      },
      {
        "X": 632.4919,
        "Y": 318.362366,
        "Z": 107.161659
      },
      {
        "X": 878.5447,
        "Y": 395.023773,
        "Z": 117.703812
      },
      {
        "X": 914.621,
        "Y": 513.845032,
        "Z": 119.391548
      },
      {
        "X": 1005.54718,
        "Y": 500.939056,
        "Z": 97.64511
      },
      {
        "X": 1158.89258,
        "Y": 349.640167,
        "Z": 90.79971
      },
      {
        "X": 932.386,
        "Y": 110.485741,
        "Z": 78.69033
      },
      {
        "X": 930.211731,
        "Y": 77.97855,
        "Z": 77.7664
      },
      {
        "X": 916.012268,
        "Y": 51.3456955,
        "Z": 79.76476
      },
      {
        "X": 898.6705,
        "Y": 22.3174877,
        "Z": 78.01519
      },
      {
        "X": 946.0838,
        "Y": -25.534111,
        "Z": 77.76434
      }
    ]
  }